{
  "project_info": {
    "project_number": "748425756908",
    "project_id": "dtc-manager",
    "storage_bucket": "dtc-manager.appspot.com"
  },
  "client": [
    {
      "client_info": {
        "mobilesdk_app_id": "1:748425756908:android:66a244b0030648b863a5c9",
        "android_client_info": {
          "package_name": "com.dantech.dtc_manager"
        }
      },
      "oauth_client": [
        {
          "client_id": "748425756908-dm9lvn8mih0fqphm18phg7n6b6j6ql2f.apps.googleusercontent.com",
          "client_type": 1,
          "android_info": {
            "package_name": "com.dantech.dtc_manager",
            "certificate_hash": "67cc2a1b18ccd7320d10b718c47a3aa2cd816964"
          }
        },
        {
          "client_id": "748425756908-2f71pb9cqhaetabodqh85sar2cta4ivc.apps.googleusercontent.com",
          "client_type": 3
        }
      ],
      "api_key": [
        {
          "current_key": "AIzaSyAgOp7-434ZvFhZXfKK4LY8-68jeAzYod8"
        }
      ],
      "services": {
        "appinvite_service": {
          "other_platform_oauth_client": [
            {
              "client_id": "748425756908-2f71pb9cqhaetabodqh85sar2cta4ivc.apps.googleusercontent.com",
              "client_type": 3
            }
          ]
        }
      }
    }
  ],
  "configuration_version": "1"
}